power_daps/__init__.py
power_daps/java/__init__.py
power_daps/java/java_command.py
power_daps/java/java_helper.py
power_daps/java/javac_command.py
power_daps/java/actions/__init__.py
power_daps/java/actions/clean_action.py
power_daps/java/actions/compile_action.py
power_daps/java/actions/compile_test_action.py
power_daps/java/actions/default_action.py
power_daps/java/actions/deps_action.py
power_daps/java/actions/init_action.py
power_daps/java/actions/run_action.py
power_daps/java/actions/unit_test_action.py
power_daps/java/templates/__init__.py
power_daps/java/templates/init/.gitignore
power_daps/java/templates/init/.talismanrc
power_daps/java/templates/init/PROJECT_NAME.iml
power_daps/java/templates/init/actions.yml
power_daps/java/templates/init/dependencies.yml
power_daps/java/templates/init/.idea/.gitignore
power_daps/java/templates/init/.idea/description.html
power_daps/java/templates/init/.idea/encodings.xml
power_daps/java/templates/init/.idea/misc.xml
power_daps/java/templates/init/.idea/modules.xml
power_daps/java/templates/init/.idea/project-template.xml
power_daps/java/templates/init/.idea/vcs.xml
power_daps/java/templates/init/.idea/codeStyles/Project.xml
power_daps/java/templates/init/.idea/codeStyles/codeStyleConfig.xml
power_daps/java/templates/init/.idea/libraries/java.xml
power_daps/java/templates/init/config/dap_config.yml
power_daps/java/templates/init/src/.gitkeep
power_daps/java/templates/init/src/org/PROJECT_NAME/Main.java
power_daps/java/templates/init/test/.gitkeep
power_daps/java/templates/init/test/org/PROJECT_NAME/MainTest.java
power_daps_meta_model_java_9-0.0.6.dist-info/METADATA
power_daps_meta_model_java_9-0.0.6.dist-info/WHEEL
power_daps_meta_model_java_9-0.0.6.dist-info/entry_points.txt
power_daps_meta_model_java_9-0.0.6.dist-info/top_level.txt
power_daps_meta_model_java_9-0.0.6.dist-info/RECORD
